rhinoMorphExtension/calWordsFreq.py
rhinoMorphExtension/compareTwoFiles.py
rhinoMorphExtension/findKeywordSentences.py
rhinoMorphExtension/linguatools.py
rhinoMorphExtension/pythonMorphExtension.py
rhinoMorphExtension-1.2.1.7.dist-info/METADATA
rhinoMorphExtension-1.2.1.7.dist-info/WHEEL
rhinoMorphExtension-1.2.1.7.dist-info/top_level.txt
rhinoMorphExtension-1.2.1.7.dist-info/RECORD
