Metadata-Version: 2.1
Name: rhinoMorphExtension
Version: 1.2.1.7
Summary: Extension Tools for rhinoMorph
Home-page: https://lingua.blog.me/221789288704
Author: Sukjae Choi
Author-email: lingua72@gmail.com
License: MIT
Platform: UNKNOWN
Requires-Python: >=3
